params_grid/__init__.py
params_grid/search_space.py
params_grid-0.2.dist-info/METADATA
params_grid-0.2.dist-info/WHEEL
params_grid-0.2.dist-info/top_level.txt
params_grid-0.2.dist-info/RECORD
