Metadata-Version: 2.1
Name: params-grid
Version: 0.2
Summary: Tool for defining and working with hyperparams of machine learning models.
Home-page: https://github.com/darkhan-ai/params-grid
Requires-Dist: optuna
Requires-Dist: pandas
